{
    "user_id": 950274278,
    "settings": {
        "theme_id": "food",
        "right_answer_count": "10",
        "session_words_count": "3"
    },
    "statistics": {
        "remembered_words_count": 0,
        "words_left": 0,
        "remembered_words_list": {
            "Cheetah": 4,
            "Camel": 777,
            "Cat": 781,
            "Gorilla": 1,
            "Dog": 2,
            "Shark": 1,
            "Octopus": 2,
            "Giraffe": 1,
            "Whale": 1,
            "Banana": 0,
            "Fish": 2,
            "Carrot": 4,
            "Sausage": 0,
            "Strawberries": 3
        }
    }
}